<?xml version="1.0" encoding="UTF-8"?>
<con:resource name="/TeeOff/v1/Reservation/BookReservation" path="/TeeOff/v1/Reservation/BookReservation" id="aecd93f2-40a9-4f6d-b937-667f730b923a" xmlns:xsi="http://www.w3.org/2001/XMLSchema-instance" xmlns:con="http://eviware.com/soapui/config"><con:settings><con:setting id="aecd93f2-40a9-4f6d-b937-667f730b923afileName">%2FTeeOff%2Fv1%2FReservation%2FBookReservation</con:setting></con:settings><con:parameters/><con:method name="ReservationController_BookReservation" id="d4c969d0-f934-4b7a-ab2f-d10c7ea381d8" method="POST"><con:description>
</con:description><con:settings/><con:parameters><con:parameter required="true"><con:name>sessionId</con:name><con:style>QUERY</con:style><con:description xsi:nil="true"/></con:parameter></con:parameters><con:representation type="REQUEST"><con:mediaType>application/json</con:mediaType><con:params/><con:sampleContent>{"CardId":0,"OriginatingContactId":0}</con:sampleContent></con:representation><con:representation type="REQUEST"><con:mediaType>text/json</con:mediaType><con:params/><con:sampleContent/></con:representation><con:representation type="REQUEST"><con:mediaType>text/html</con:mediaType><con:params/><con:sampleContent/></con:representation><con:representation type="REQUEST"><con:mediaType>application/html</con:mediaType><con:params/><con:sampleContent/></con:representation><con:representation type="REQUEST"><con:mediaType>application/octet-stream</con:mediaType><con:params/><con:sampleContent/></con:representation><con:representation type="REQUEST"><con:mediaType>application/xml</con:mediaType><con:params/><con:sampleContent/></con:representation><con:representation type="REQUEST"><con:mediaType>text/xml</con:mediaType><con:params/><con:sampleContent/></con:representation><con:representation type="REQUEST"><con:mediaType>application/x-www-form-urlencoded</con:mediaType><con:params/><con:sampleContent/></con:representation><con:representation type="RESPONSE"><con:mediaType>application/json</con:mediaType><con:status>200</con:status><con:params/><con:sampleContent>{}</con:sampleContent></con:representation><con:representation type="RESPONSE"><con:mediaType>text/json</con:mediaType><con:status>200</con:status><con:params/><con:sampleContent xsi:nil="true"/></con:representation><con:representation type="RESPONSE"><con:mediaType>text/html</con:mediaType><con:status>200</con:status><con:params/><con:sampleContent xsi:nil="true"/></con:representation><con:representation type="RESPONSE"><con:mediaType>application/html</con:mediaType><con:status>200</con:status><con:params/><con:sampleContent xsi:nil="true"/></con:representation><con:representation type="RESPONSE"><con:mediaType>application/octet-stream</con:mediaType><con:status>200</con:status><con:params/><con:sampleContent xsi:nil="true"/></con:representation><con:representation type="RESPONSE"><con:mediaType>application/xml</con:mediaType><con:status>200</con:status><con:params/><con:sampleContent xsi:nil="true"/></con:representation><con:representation type="RESPONSE"><con:mediaType>text/xml</con:mediaType><con:status>200</con:status><con:params/><con:sampleContent xsi:nil="true"/></con:representation><con:representation type="REQUEST"><con:mediaType>application/json</con:mediaType><con:params/></con:representation><con:representation type="REQUEST"><con:mediaType>text/json</con:mediaType><con:params/></con:representation><con:representation type="REQUEST"><con:mediaType>text/html</con:mediaType><con:params/></con:representation><con:representation type="REQUEST"><con:mediaType>application/html</con:mediaType><con:params/></con:representation><con:representation type="REQUEST"><con:mediaType>application/octet-stream</con:mediaType><con:params/></con:representation><con:representation type="REQUEST"><con:mediaType>application/xml</con:mediaType><con:params/></con:representation><con:representation type="REQUEST"><con:mediaType>text/xml</con:mediaType><con:params/></con:representation><con:representation type="REQUEST"><con:mediaType>application/x-www-form-urlencoded</con:mediaType><con:params/></con:representation><con:representation type="RESPONSE"><con:mediaType>application/json; charset=utf-8</con:mediaType><con:status>200</con:status><con:params/><con:element xmlns:book="https://dev-api.opentee.com/TeeOff/v1/Reservation/BookReservation">book:Response</con:element></con:representation><con:representation type="FAULT"><con:mediaType>application/json; charset=utf-8</con:mediaType><con:status>400</con:status><con:params/><con:element xmlns:book="https://dev-api.opentee.com/TeeOff/v1/Reservation/BookReservation">book:Fault</con:element></con:representation><con:representation type="FAULT"><con:mediaType>text/plain; charset=utf-8</con:mediaType><con:status>500</con:status><con:params/><con:element>data</con:element></con:representation><con:request name="Request 1" id="85a5abc3-65fd-41f9-bdc9-00553f147054" mediaType="application/json"><con:settings/><con:endpoint>https://dev-api.opentee.com</con:endpoint><con:request>{"CardId":0,"OriginatingContactId":0}</con:request><con:credentials><con:selectedAuthProfile>Inherit From Parent</con:selectedAuthProfile><con:authType>No Authorization</con:authType></con:credentials><con:jmsConfig JMSDeliveryMode="PERSISTENT"/><con:parameters/></con:request><con:request name="Request 2" id="9d2dea89-9f19-42ec-95ed-8daa5a9cab82" mediaType="text/json"><con:settings/><con:endpoint>https://dev-api.opentee.com</con:endpoint><con:request/><con:credentials><con:selectedAuthProfile>Inherit From Parent</con:selectedAuthProfile><con:authType>No Authorization</con:authType></con:credentials><con:jmsConfig JMSDeliveryMode="PERSISTENT"/><con:parameters/></con:request><con:request name="Request 3" id="23c99288-2c72-4ef2-b1c6-f59b983bb67c" mediaType="text/html"><con:settings/><con:endpoint>https://dev-api.opentee.com</con:endpoint><con:request/><con:credentials><con:selectedAuthProfile>Inherit From Parent</con:selectedAuthProfile><con:authType>No Authorization</con:authType></con:credentials><con:jmsConfig JMSDeliveryMode="PERSISTENT"/><con:parameters/></con:request><con:request name="Request 4" id="791ae663-c7d0-43ef-8171-28f87f739340" mediaType="application/html"><con:settings/><con:endpoint>https://dev-api.opentee.com</con:endpoint><con:request/><con:credentials><con:selectedAuthProfile>Inherit From Parent</con:selectedAuthProfile><con:authType>No Authorization</con:authType></con:credentials><con:jmsConfig JMSDeliveryMode="PERSISTENT"/><con:parameters/></con:request><con:request name="Request 5" id="4475f28b-0b05-49c2-866f-0b044cda0ccb" mediaType="application/octet-stream"><con:settings/><con:endpoint>https://dev-api.opentee.com</con:endpoint><con:request/><con:credentials><con:selectedAuthProfile>Inherit From Parent</con:selectedAuthProfile><con:authType>No Authorization</con:authType></con:credentials><con:jmsConfig JMSDeliveryMode="PERSISTENT"/><con:parameters/></con:request><con:request name="Request 6" id="23df9916-977c-4f26-893e-d8e72f82a566" mediaType="application/xml"><con:settings/><con:endpoint>https://dev-api.opentee.com</con:endpoint><con:request/><con:credentials><con:selectedAuthProfile>Inherit From Parent</con:selectedAuthProfile><con:authType>No Authorization</con:authType></con:credentials><con:jmsConfig JMSDeliveryMode="PERSISTENT"/><con:parameters/></con:request><con:request name="Request 7" id="e2497c08-3727-46cf-b96f-5c3ae166f2dc" mediaType="text/xml"><con:settings/><con:endpoint>https://dev-api.opentee.com</con:endpoint><con:request/><con:credentials><con:selectedAuthProfile>Inherit From Parent</con:selectedAuthProfile><con:authType>No Authorization</con:authType></con:credentials><con:jmsConfig JMSDeliveryMode="PERSISTENT"/><con:parameters/></con:request><con:request name="Request 8" id="3932ed34-a4be-4d6b-bd36-8c81b91f82fa" mediaType="application/x-www-form-urlencoded"><con:settings/><con:endpoint>https://dev-api.opentee.com</con:endpoint><con:request/><con:credentials><con:selectedAuthProfile>Inherit From Parent</con:selectedAuthProfile><con:authType>No Authorization</con:authType></con:credentials><con:jmsConfig JMSDeliveryMode="PERSISTENT"/><con:parameters/></con:request></con:method></con:resource>