<?xml version="1.0" encoding="UTF-8"?>
<con:resource name="/api/Test/GetActiveFloatingBarterCourses/{channelId}" path="/api/Test/GetActiveFloatingBarterCourses/{channelId}" id="85eb22fc-62d7-4d53-961f-6d200b298001" xmlns:xsi="http://www.w3.org/2001/XMLSchema-instance" xmlns:con="http://eviware.com/soapui/config"><con:settings><con:setting id="187ecac7-bf07-4a3c-862a-16a2f4ad803ffileName">%2Fapi%2FTest%2FGetActiveFloatingBarterCourses%2F%7BchannelId%7D</con:setting><con:setting id="85eb22fc-62d7-4d53-961f-6d200b298001fileName">%2Fapi%2FTest%2FGetActiveFloatingBarterCourses%2F%7BchannelId%7D</con:setting></con:settings><con:parameters><con:parameter required="true"><con:name>channelId</con:name><con:value/><con:style>TEMPLATE</con:style><con:default/><con:description xsi:nil="true"/></con:parameter></con:parameters><con:method name="Test_GetActiveFloatingBarterCourses" id="b371f9fd-d68e-4909-84d1-eb5e92930e9e" method="GET"><con:description>
</con:description><con:settings/><con:parameters><con:parameter required="false"><con:name>date</con:name><con:value/><con:style>QUERY</con:style><con:type xmlns:xs="http://www.w3.org/2001/XMLSchema">xs:string</con:type><con:description xsi:nil="true"/></con:parameter></con:parameters><con:representation type="RESPONSE" id=""><con:mediaType>application/json</con:mediaType><con:status/><con:params/><con:description xsi:nil="true"/><con:sampleContent xsi:nil="true"/></con:representation><con:request name="Request 1" id="fcb2126e-ca79-49a5-843e-5289bf775eb0" mediaType="application/json"><con:description xsi:nil="true"/><con:settings/><con:endpoint>https://dist-dev.ezlinks.com</con:endpoint><con:request/><con:credentials><con:selectedAuthProfile>No Authorization</con:selectedAuthProfile><con:authType>No Authorization</con:authType></con:credentials><con:jmsConfig JMSDeliveryMode="PERSISTENT"/><con:parameters><entry key="channelId" value="" xmlns="http://eviware.com/soapui/config"/></con:parameters><con:parameterOrder><con:entry>channelId</con:entry><con:entry>date</con:entry></con:parameterOrder></con:request></con:method></con:resource>