<?xml version="1.0" encoding="UTF-8"?>
<con:testCase id="a376f474-9115-4f76-911c-0a8ab27f9244" discardOkResults="true" failOnError="false" failTestCaseOnErrors="true" keepSession="true" name="AddConfirmationNote" searchProperties="true" timeout="0" xmlns:con="http://eviware.com/soapui/config"><con:settings><con:setting id="a376f474-9115-4f76-911c-0a8ab27f9244fileName">AddConfirmationNote</con:setting></con:settings><con:savedRecentRuns>1</con:savedRecentRuns><con:testStep type="restrequest" name="REST Request - Valid" id="c80f9fd3-b330-40a2-9a9e-1667fee61bc8"><con:settings/><con:config service="API.EZLinks" resourcePath="/ETNObject.asp" methodName="TeeTimeReservations_AddConfirmationNote" xsi:type="con:RestRequestStep" xmlns:xsi="http://www.w3.org/2001/XMLSchema-instance"><con:restRequest name="REST Request - Valid" id="8de13891-11d2-4540-baf2-d584b53e486d" mediaType="application/json"><con:settings><con:setting id="com.eviware.soapui.impl.wsdl.WsdlRequest@request-headers">&lt;xml-fragment/></con:setting></con:settings><con:endpoint>https://api.ezlinks.com</con:endpoint><con:request/><con:originalUri>https://api.ezlinks.com/ETNObject.asp</con:originalUri><con:assertion type="XPath Match" id="3bfc108c-9ee0-42c0-a691-3c63fd5fe2ee" name="Correct ConfirmID"><con:configuration><path>//AddConfirmationNote[1]/AddConfirmationNoteRecord[1]/ConfirmID[1]</path><content>${REST Request - Valid#Param3}</content><allowWildcards>false</allowWildcards><ignoreNamspaceDifferences>false</ignoreNamspaceDifferences><ignoreComments>false</ignoreComments></con:configuration></con:assertion><con:assertion type="Simple Contains" id="53701442-8871-4300-be7d-376c00e45363" name="Contains Test Confirmation Note"><con:configuration><token>Test Confirmation Note</token><ignoreCase>false</ignoreCase><useRegEx>false</useRegEx></con:configuration></con:assertion><con:credentials><con:selectedAuthProfile>Inherit From Parent</con:selectedAuthProfile><con:authType>No Authorization</con:authType></con:credentials><con:jmsConfig JMSDeliveryMode="PERSISTENT"/><con:parameters>
  <con:entry key="DOM" value="1"/>
  <con:entry key="Subscriber" value="XMLDemo"/>
  <con:entry key="ObjectId" value="AddConfirmationNote"/>
  <con:entry key="Timeout" value="60"/>
  <con:entry key="Param4" value="Test Confirmation Note"/>
  <con:entry key="Param3" value="${#[API.EZLinks#TeeTimeReserve#REST Request - Valid]#ResponseAsXml#//TeeTimeReserve[1]/TeeTimeReserveRecord[1]/ConfirmID[1]}"/>
  <con:entry key="Param2" value="limesource?01"/>
  <con:entry key="Param1" value="user1@gmail.com"/>
  <con:entry key="Password" value="ttdemo14"/>
</con:parameters><con:parameterOrder><con:entry>DOM</con:entry><con:entry>Timeout</con:entry><con:entry>Subscriber</con:entry><con:entry>Password</con:entry><con:entry>ObjectId</con:entry><con:entry>Param1</con:entry><con:entry>Param2</con:entry><con:entry>Param3</con:entry><con:entry>Param4</con:entry></con:parameterOrder></con:restRequest></con:config></con:testStep><con:testStep type="restrequest" name="REST Request - Empty Param1/InternetUserID" id="e9942cfa-89d1-4667-85e2-39c33fd7aa2b"><con:settings/><con:config service="API.EZLinks" resourcePath="/ETNObject.asp" methodName="TeeTimeReservations_AddConfirmationNote" xsi:type="con:RestRequestStep" xmlns:xsi="http://www.w3.org/2001/XMLSchema-instance"><con:restRequest name="REST Request - Empty Param1/InternetUserID" id="8de13891-11d2-4540-baf2-d584b53e486d" mediaType="application/json"><con:settings><con:setting id="com.eviware.soapui.impl.wsdl.WsdlRequest@request-headers">&lt;xml-fragment/></con:setting></con:settings><con:endpoint>https://api.ezlinks.com</con:endpoint><con:request/><con:originalUri>https://api.ezlinks.com/ETNObject.asp</con:originalUri><con:assertion type="XPath Match" id="f52074a7-8f6a-4b8d-aef2-62f4dc0b787d" name="INVALID_USERID"><con:configuration><path>//Error[1]/ErrorDescription[1]</path><content>INVALID_USERID</content><allowWildcards>false</allowWildcards><ignoreNamspaceDifferences>false</ignoreNamspaceDifferences><ignoreComments>false</ignoreComments></con:configuration></con:assertion><con:credentials><con:selectedAuthProfile>Inherit From Parent</con:selectedAuthProfile><con:authType>No Authorization</con:authType></con:credentials><con:jmsConfig JMSDeliveryMode="PERSISTENT"/><con:parameters>
  <con:entry key="DOM" value="1"/>
  <con:entry key="Subscriber" value="XMLDemo"/>
  <con:entry key="ObjectId" value="AddConfirmationNote"/>
  <con:entry key="Timeout" value="60"/>
  <con:entry key="Param4" value="Test Confirmation Note"/>
  <con:entry key="Param3" value="${#[API.EZLinks#TeeTimeReserve#REST Request - Valid]#ResponseAsXml#//TeeTimeReserve[1]/TeeTimeReserveRecord[1]/ConfirmID[1]}"/>
  <con:entry key="Param2" value="limesource?01"/>
  <con:entry key="Password" value="ttdemo14"/>
</con:parameters><con:parameterOrder><con:entry>DOM</con:entry><con:entry>Timeout</con:entry><con:entry>Subscriber</con:entry><con:entry>Password</con:entry><con:entry>ObjectId</con:entry><con:entry>Param1</con:entry><con:entry>Param2</con:entry><con:entry>Param3</con:entry><con:entry>Param4</con:entry></con:parameterOrder></con:restRequest></con:config></con:testStep><con:testStep type="restrequest" name="REST Request - Empty Param2/InternetPassword" id="c336bef9-0db0-4d5f-8143-872548bd9ebc"><con:settings/><con:config service="API.EZLinks" resourcePath="/ETNObject.asp" methodName="TeeTimeReservations_AddConfirmationNote" xsi:type="con:RestRequestStep" xmlns:xsi="http://www.w3.org/2001/XMLSchema-instance"><con:restRequest name="REST Request - Empty Param2/InternetPassword" id="8de13891-11d2-4540-baf2-d584b53e486d" mediaType="application/json"><con:settings><con:setting id="com.eviware.soapui.impl.wsdl.WsdlRequest@request-headers">&lt;xml-fragment/></con:setting></con:settings><con:endpoint>https://api.ezlinks.com</con:endpoint><con:request/><con:originalUri>https://api.ezlinks.com/ETNObject.asp</con:originalUri><con:assertion type="XPath Match" id="0c40876d-3a32-4085-b40a-bb7198579c14" name="INVALID_PASSWORD"><con:configuration><path>//Error[1]/ErrorDescription[1]</path><content>INVALID_PASSWORD</content><allowWildcards>false</allowWildcards><ignoreNamspaceDifferences>false</ignoreNamspaceDifferences><ignoreComments>false</ignoreComments></con:configuration></con:assertion><con:credentials><con:selectedAuthProfile>Inherit From Parent</con:selectedAuthProfile><con:authType>No Authorization</con:authType></con:credentials><con:jmsConfig JMSDeliveryMode="PERSISTENT"/><con:parameters>
  <con:entry key="DOM" value="1"/>
  <con:entry key="Subscriber" value="XMLDemo"/>
  <con:entry key="ObjectId" value="AddConfirmationNote"/>
  <con:entry key="Timeout" value="60"/>
  <con:entry key="Param4" value="Test Confirmation Note"/>
  <con:entry key="Param3" value="${#[API.EZLinks#TeeTimeReserve#REST Request - Valid]#ResponseAsXml#//TeeTimeReserve[1]/TeeTimeReserveRecord[1]/ConfirmID[1]}"/>
  <con:entry key="Param1" value="user1@gmail.com"/>
  <con:entry key="Password" value="ttdemo14"/>
</con:parameters><con:parameterOrder><con:entry>DOM</con:entry><con:entry>Timeout</con:entry><con:entry>Subscriber</con:entry><con:entry>Password</con:entry><con:entry>ObjectId</con:entry><con:entry>Param1</con:entry><con:entry>Param2</con:entry><con:entry>Param3</con:entry><con:entry>Param4</con:entry></con:parameterOrder></con:restRequest></con:config></con:testStep><con:testStep type="restrequest" name="REST Request - Empty Param3/ConfirmID" id="ed838e44-e9e6-4e4a-9387-e412a0a95fbd"><con:settings/><con:config service="API.EZLinks" resourcePath="/ETNObject.asp" methodName="TeeTimeReservations_AddConfirmationNote" xsi:type="con:RestRequestStep" xmlns:xsi="http://www.w3.org/2001/XMLSchema-instance"><con:restRequest name="REST Request - Empty Param3/ConfirmID" id="8de13891-11d2-4540-baf2-d584b53e486d" mediaType="application/json"><con:settings><con:setting id="com.eviware.soapui.impl.wsdl.WsdlRequest@request-headers">&lt;xml-fragment/></con:setting></con:settings><con:endpoint>https://api.ezlinks.com</con:endpoint><con:request/><con:originalUri>https://api.ezlinks.com/ETNObject.asp</con:originalUri><con:assertion type="XPath Match" id="0c40876d-3a32-4085-b40a-bb7198579c14" name="INVALID_CONFIRMATIONID"><con:configuration><path>//Error[1]/ErrorDescription[1]</path><content>INVALID_CONFIRMATIONID</content><allowWildcards>false</allowWildcards><ignoreNamspaceDifferences>false</ignoreNamspaceDifferences><ignoreComments>false</ignoreComments></con:configuration></con:assertion><con:credentials><con:selectedAuthProfile>Inherit From Parent</con:selectedAuthProfile><con:authType>No Authorization</con:authType></con:credentials><con:jmsConfig JMSDeliveryMode="PERSISTENT"/><con:parameters>
  <con:entry key="DOM" value="1"/>
  <con:entry key="Subscriber" value="XMLDemo"/>
  <con:entry key="ObjectId" value="AddConfirmationNote"/>
  <con:entry key="Timeout" value="60"/>
  <con:entry key="Param4" value="Test Confirmation Note"/>
  <con:entry key="Param2" value="limesource?01"/>
  <con:entry key="Param1" value="user1@gmail.com"/>
  <con:entry key="Password" value="ttdemo14"/>
</con:parameters><con:parameterOrder><con:entry>DOM</con:entry><con:entry>Timeout</con:entry><con:entry>Subscriber</con:entry><con:entry>Password</con:entry><con:entry>ObjectId</con:entry><con:entry>Param1</con:entry><con:entry>Param2</con:entry><con:entry>Param3</con:entry><con:entry>Param4</con:entry></con:parameterOrder></con:restRequest></con:config></con:testStep><con:testStep type="restrequest" name="REST Request - Empty Param4/ConfirmationNote" id="a58595b9-ac10-4f18-9ac1-eed236e9ebb2"><con:settings/><con:config service="API.EZLinks" resourcePath="/ETNObject.asp" methodName="TeeTimeReservations_AddConfirmationNote" xsi:type="con:RestRequestStep" xmlns:xsi="http://www.w3.org/2001/XMLSchema-instance"><con:restRequest name="REST Request - Empty Param4/ConfirmationNote" id="8de13891-11d2-4540-baf2-d584b53e486d" mediaType="application/json"><con:settings><con:setting id="com.eviware.soapui.impl.wsdl.WsdlRequest@request-headers">&lt;xml-fragment/></con:setting></con:settings><con:endpoint>https://api.ezlinks.com</con:endpoint><con:request/><con:originalUri>https://api.ezlinks.com/ETNObject.asp</con:originalUri><con:assertion type="Simple Contains" id="6e74d800-b04d-489b-b107-687c4ed98c69" name="Contains AddConfirmationNoteRecord"><con:configuration><token>AddConfirmationNoteRecord</token><ignoreCase>false</ignoreCase><useRegEx>false</useRegEx></con:configuration></con:assertion><con:credentials><con:selectedAuthProfile>Inherit From Parent</con:selectedAuthProfile><con:authType>No Authorization</con:authType></con:credentials><con:jmsConfig JMSDeliveryMode="PERSISTENT"/><con:parameters>
  <con:entry key="DOM" value="1"/>
  <con:entry key="Subscriber" value="XMLDemo"/>
  <con:entry key="ObjectId" value="AddConfirmationNote"/>
  <con:entry key="Timeout" value="60"/>
  <con:entry key="Param3" value="${#[API.EZLinks#TeeTimeReserve#REST Request - Valid]#ResponseAsXml#//TeeTimeReserve[1]/TeeTimeReserveRecord[1]/ConfirmID[1]}"/>
  <con:entry key="Param2" value="limesource?01"/>
  <con:entry key="Param1" value="user1@gmail.com"/>
  <con:entry key="Password" value="ttdemo14"/>
</con:parameters><con:parameterOrder><con:entry>DOM</con:entry><con:entry>Timeout</con:entry><con:entry>Subscriber</con:entry><con:entry>Password</con:entry><con:entry>ObjectId</con:entry><con:entry>Param1</con:entry><con:entry>Param2</con:entry><con:entry>Param3</con:entry><con:entry>Param4</con:entry></con:parameterOrder></con:restRequest></con:config></con:testStep><con:properties/><con:reportParameters/></con:testCase>